[{"feature_1":0.496714153,"feature_2":0.3551770788,"feature_3":0.2841358125,"feature_4":-0.8289950109,"feature_5":-1.5944276588,"company_name":null,"person_name":null,"email":null,"website":null,"country":null,"issues":"missing_company_name;missing_person_name;missing_email;missing_country","has_issues":true,"suggested_email":null,"suggested_country":null,"email_confidence":0.0,"country_confidence":0.0,"corrections_applied":"","is_duplicate":false,"duplicate_group":null,"role_function":"Other","role_confidence":0.0},{"feature_1":-0.1382643012,"feature_2":-0.1803288334,"feature_3":-0.0130536979,"feature_4":-0.5601810402,"feature_5":-0.599375023,"company_name":null,"person_name":null,"email":null,"website":null,"country":null,"issues":"missing_company_name;missing_person_name;missing_email;missing_country","has_issues":true,"suggested_email":null,"suggested_country":null,"email_confidence":0.0,"country_confidence":0.0,"corrections_applied":"","is_duplicate":true,"duplicate_group":null,"role_function":"Other","role_confidence":0.0},{"feature_1":0.6476885381,"feature_2":0.6134170864,"feature_3":0.4321493934,"feature_4":0.7472936051,"feature_5":0.0052436997,"company_name":null,"person_name":null,"email":null,"website":null,"country":null,"issues":"missing_company_name;missing_person_name;missing_email;missing_country","has_issues":true,"suggested_email":null,"suggested_country":null,"email_confidence":0.0,"country_confidence":0.0,"corrections_applied":"","is_duplicate":true,"duplicate_group":null,"role_function":"Other","role_confidence":0.0},{"feature_1":1.5230298564,"feature_2":1.4428021295,"feature_3":0.8668951334,"feature_4":0.6103702654,"feature_5":0.0469805938,"company_name":null,"person_name":null,"email":null,"website":null,"country":null,"issues":"missing_company_name;missing_person_name;missing_email;missing_country","has_issues":true,"suggested_email":null,"suggested_country":null,"email_confidence":0.0,"country_confidence":0.0,"corrections_applied":"","is_duplicate":true,"duplicate_group":null,"role_function":"Other","role_confidence":0.0},{"feature_1":-0.2341533747,"feature_2":-0.2502819459,"feature_3":-0.2548436242,"feature_4":-0.020901594,"feature_5":-0.4500654715,"company_name":null,"person_name":null,"email":null,"website":null,"country":null,"issues":"missing_company_name;missing_person_name;missing_email;missing_country","has_issues":true,"suggested_email":null,"suggested_country":null,"email_confidence":0.0,"country_confidence":0.0,"corrections_applied":"","is_duplicate":true,"duplicate_group":null,"role_function":"Other","role_confidence":0.0},{"feature_1":-0.2341369569,"feature_2":-0.1937318713,"feature_3":-0.2108509825,"feature_4":0.1173273833,"feature_5":0.6228499323,"company_name":null,"person_name":null,"email":null,"website":null,"country":null,"issues":"missing_company_name;missing_person_name;missing_email;missing_country","has_issues":true,"suggested_email":null,"suggested_country":null,"email_confidence":0.0,"country_confidence":0.0,"corrections_applied":"","is_duplicate":true,"duplicate_group":null,"role_function":"Other","role_confidence":0.0},{"feature_1":1.5792128155,"feature_2":1.7678314056,"feature_3":0.8411099345,"feature_4":1.2776648958,"feature_5":-1.0676204294,"company_name":null,"person_name":null,"email":null,"website":null,"country":null,"issues":"missing_company_name;missing_person_name;missing_email;missing_country","has_issues":true,"suggested_email":null,"suggested_country":null,"email_confidence":0.0,"country_confidence":0.0,"corrections_applied":"","is_duplicate":true,"duplicate_group":null,"role_function":"Other","role_confidence":0.0},{"feature_1":0.7674347292,"feature_2":0.7848925104,"feature_3":0.4350959597,"feature_4":-0.5915713888,"feature_5":-0.142379485,"company_name":null,"person_name":null,"email":null,"website":null,"country":null,"issues":"missing_company_name;missing_person_name;missing_email;missing_country","has_issues":true,"suggested_email":null,"suggested_country":null,"email_confidence":0.0,"country_confidence":0.0,"corrections_applied":"","is_duplicate":true,"duplicate_group":null,"role_function":"Other","role_confidence":0.0},{"feature_1":-0.4694743859,"feature_2":-0.4437193469,"feature_3":-0.1832324243,"feature_4":0.5470973812,"feature_5":0.1202956317,"company_name":null,"person_name":null,"email":null,"website":null,"country":null,"issues":"missing_company_name;missing_person_name;missing_email;missing_country","has_issues":true,"suggested_email":null,"suggested_country":null,"email_confidence":0.0,"country_confidence":0.0,"corrections_applied":"","is_duplicate":true,"duplicate_group":null,"role_function":"Other","role_confidence":0.0},{"feature_1":0.5425600436,"feature_2":0.535115452,"feature_3":0.6565531709,"feature_4":-0.2021926524,"feature_5":0.5144388341,"company_name":null,"person_name":null,"email":null,"website":null,"country":null,"issues":"missing_company_name;missing_person_name;missing_email;missing_country","has_issues":true,"suggested_email":null,"suggested_country":null,"email_confidence":0.0,"country_confidence":0.0,"corrections_applied":"","is_duplicate":true,"duplicate_group":null,"role_function":"Other","role_confidence":0.0},{"feature_1":-0.4634176928,"feature_2":-0.6552948143,"feature_3":-0.1746197953,"feature_4":-0.2176812032,"feature_5":0.7116148781,"company_name":null,"person_name":null,"email":null,"website":null,"country":null,"issues":"missing_company_name;missing_person_name;missing_email;missing_country","has_issues":true,"suggested_email":null,"suggested_country":null,"email_confidence":0.0,"country_confidence":0.0,"corrections_applied":"","is_duplicate":true,"duplicate_group":null,"role_function":"Other","role_confidence":0.0},{"feature_1":-0.4657297536,"feature_2":-0.4683811411,"feature_3":-0.1193083128,"feature_4":1.098776852,"feature_5":-1.1246420918,"company_name":null,"person_name":null,"email":null,"website":null,"country":null,"issues":"missing_company_name;missing_person_name;missing_email;missing_country","has_issues":true,"suggested_email":null,"suggested_country":null,"email_confidence":0.0,"country_confidence":0.0,"corrections_applied":"","is_duplicate":true,"duplicate_group":null,"role_function":"Other","role_confidence":0.0},{"feature_1":0.2419622716,"feature_2":0.2479852926,"feature_3":0.2163813121,"feature_4":0.825416349,"feature_5":-1.5341141707,"company_name":null,"person_name":null,"email":null,"website":null,"country":null,"issues":"missing_company_name;missing_person_name;missing_email;missing_country","has_issues":true,"suggested_email":null,"suggested_country":null,"email_confidence":0.0,"country_confidence":0.0,"corrections_applied":"","is_duplicate":true,"duplicate_group":null,"role_function":"Other","role_confidence":0.0},{"feature_1":-1.9132802447,"feature_2":-1.6669560334,"feature_3":-0.8915009972,"feature_4":0.813509636,"feature_5":1.2776768219,"company_name":null,"person_name":null,"email":null,"website":null,"country":null,"issues":"missing_company_name;missing_person_name;missing_email;missing_country","has_issues":true,"suggested_email":null,"suggested_country":null,"email_confidence":0.0,"country_confidence":0.0,"corrections_applied":"","is_duplicate":true,"duplicate_group":null,"role_function":"Other","role_confidence":0.0},{"feature_1":-1.7249178325,"feature_2":-1.744153929,"feature_3":-0.8939858407,"feature_4":1.3054788072,"feature_5":0.332314012,"company_name":null,"person_name":null,"email":null,"website":null,"country":null,"issues":"missing_company_name;missing_person_name;missing_email;missing_country","has_issues":true,"suggested_email":null,"suggested_country":null,"email_confidence":0.0,"country_confidence":0.0,"corrections_applied":"","is_duplicate":true,"duplicate_group":null,"role_function":"Other","role_confidence":0.0},{"feature_1":-0.5622875292,"feature_2":-0.532132795,"feature_3":-0.2052468426,"feature_4":0.0210038416,"feature_5":-0.7484865366,"company_name":null,"person_name":null,"email":null,"website":null,"country":null,"issues":"missing_company_name;missing_person_name;missing_email;missing_country","has_issues":true,"suggested_email":null,"suggested_country":null,"email_confidence":0.0,"country_confidence":0.0,"corrections_applied":"","is_duplicate":true,"duplicate_group":null,"role_function":"Other","role_confidence":0.0},{"feature_1":-1.0128311203,"feature_2":-1.0163022973,"feature_3":-0.5836980816,"feature_4":0.6819529713,"feature_5":1.5511519755,"company_name":null,"person_name":null,"email":null,"website":null,"country":null,"issues":"missing_company_name;missing_person_name;missing_email;missing_country","has_issues":true,"suggested_email":null,"suggested_country":null,"email_confidence":0.0,"country_confidence":0.0,"corrections_applied":"","is_duplicate":true,"duplicate_group":null,"role_function":"Other","role_confidence":0.0},{"feature_1":0.3142473326,"feature_2":0.1973795288,"feature_3":0.1334418056,"feature_4":-0.3102667566,"feature_5":0.1156746343,"company_name":null,"person_name":null,"email":null,"website":null,"country":null,"issues":"missing_company_name;missing_person_name;missing_email;missing_country","has_issues":true,"suggested_email":null,"suggested_country":null,"email_confidence":0.0,"country_confidence":0.0,"corrections_applied":"","is_duplicate":true,"duplicate_group":null,"role_function":"Other","role_confidence":0.0},{"feature_1":-0.9080240755,"feature_2":-0.7937417941,"feature_3":-0.5025483925,"feature_4":0.3241663525,"feature_5":1.1792971841,"company_name":null,"person_name":null,"email":null,"website":null,"country":null,"issues":"missing_company_name;missing_person_name;missing_email;missing_country","has_issues":true,"suggested_email":null,"suggested_country":null,"email_confidence":0.0,"country_confidence":0.0,"corrections_applied":"","is_duplicate":true,"duplicate_group":null,"role_function":"Other","role_confidence":0.0},{"feature_1":-1.4123037013,"feature_2":-1.3371103981,"feature_3":-0.6979644367,"feature_4":-0.1301430544,"feature_5":0.0675184814,"company_name":null,"person_name":null,"email":null,"website":null,"country":null,"issues":"missing_company_name;missing_person_name;missing_email;missing_country","has_issues":true,"suggested_email":null,"suggested_country":null,"email_confidence":0.0,"country_confidence":0.0,"corrections_applied":"","is_duplicate":true,"duplicate_group":null,"role_function":"Other","role_confidence":0.0},{"feature_1":1.4656487689,"feature_2":1.5447519636,"feature_3":0.9642902411,"feature_4":0.096995965,"feature_5":2.0607479249,"company_name":null,"person_name":null,"email":null,"website":null,"country":null,"issues":"missing_company_name;missing_person_name;missing_email;missing_country","has_issues":true,"suggested_email":null,"suggested_country":null,"email_confidence":0.0,"country_confidence":0.0,"corrections_applied":"","is_duplicate":true,"duplicate_group":null,"role_function":"Other","role_confidence":0.0},{"feature_1":-0.2257763005,"feature_2":-0.316715046,"feature_3":-0.2996146695,"feature_4":0.5951570254,"feature_5":1.7553408424,"company_name":null,"person_name":null,"email":null,"website":null,"country":null,"issues":"missing_company_name;missing_person_name;missing_email;missing_country","has_issues":true,"suggested_email":null,"suggested_country":null,"email_confidence":0.0,"country_confidence":0.0,"corrections_applied":"","is_duplicate":true,"duplicate_group":null,"role_function":"Other","role_confidence":0.0},{"feature_1":0.0675282047,"feature_2":0.2078076358,"feature_3":0.1023901214,"feature_4":-0.8182206832,"feature_5":-0.2489641485,"company_name":null,"person_name":null,"email":null,"website":null,"country":null,"issues":"missing_company_name;missing_person_name;missing_email;missing_country","has_issues":true,"suggested_email":null,"suggested_country":null,"email_confidence":0.0,"country_confidence":0.0,"corrections_applied":"","is_duplicate":true,"duplicate_group":null,"role_function":"Other","role_confidence":0.0},{"feature_1":-1.4247481862,"feature_2":-1.5649332925,"feature_3":-0.8736456802,"feature_4":2.0923872757,"feature_5":0.971570951,"company_name":null,"person_name":null,"email":null,"website":null,"country":null,"issues":"missing_company_name;missing_person_name;missing_email;missing_country","has_issues":true,"suggested_email":null,"suggested_country":null,"email_confidence":0.0,"country_confidence":0.0,"corrections_applied":"","is_duplicate":true,"duplicate_group":null,"role_function":"Other","role_confidence":0.0},{"feature_1":-0.5443827245,"feature_2":-0.4856970151,"feature_3":-0.3193845488,"feature_4":-1.0060173815,"feature_5":0.6453759496,"company_name":null,"person_name":null,"email":null,"website":null,"country":null,"issues":"missing_company_name;missing_person_name;missing_email;missing_country","has_issues":true,"suggested_email":null,"suggested_country":null,"email_confidence":0.0,"country_confidence":0.0,"corrections_applied":"","is_duplicate":true,"duplicate_group":null,"role_function":"Other","role_confidence":0.0},{"feature_1":0.1109225897,"feature_2":0.3299681523,"feature_3":0.1643563546,"feature_4":-1.2141886128,"feature_5":1.3686315575,"company_name":null,"person_name":null,"email":null,"website":null,"country":null,"issues":"missing_company_name;missing_person_name;missing_email;missing_country","has_issues":true,"suggested_email":null,"suggested_country":null,"email_confidence":0.0,"country_confidence":0.0,"corrections_applied":"","is_duplicate":true,"duplicate_group":null,"role_function":"Other","role_confidence":0.0},{"feature_1":-1.1509935774,"feature_2":-1.2500472099,"feature_3":-0.5690687868,"feature_4":1.1581108735,"feature_5":-0.9649234606,"company_name":null,"person_name":null,"email":null,"website":null,"country":null,"issues":"missing_company_name;missing_person_name;missing_email;missing_country","has_issues":true,"suggested_email":null,"suggested_country":null,"email_confidence":0.0,"country_confidence":0.0,"corrections_applied":"","is_duplicate":true,"duplicate_group":null,"role_function":"Other","role_confidence":0.0},{"feature_1":0.3756980183,"feature_2":0.3190682454,"feature_3":0.0800745314,"feature_4":0.791662694,"feature_5":0.68605146,"company_name":null,"person_name":null,"email":null,"website":null,"country":null,"issues":"missing_company_name;missing_person_name;missing_email;missing_country","has_issues":true,"suggested_email":null,"suggested_country":null,"email_confidence":0.0,"country_confidence":0.0,"corrections_applied":"","is_duplicate":true,"duplicate_group":null,"role_function":"Other","role_confidence":0.0},{"feature_1":-0.6006386899,"feature_2":-0.5906735534,"feature_3":-0.3718497159,"feature_4":0.6241198171,"feature_5":1.0584244868,"company_name":null,"person_name":null,"email":null,"website":null,"country":null,"issues":"missing_company_name;missing_person_name;missing_email;missing_country","has_issues":true,"suggested_email":null,"suggested_country":null,"email_confidence":0.0,"country_confidence":0.0,"corrections_applied":"","is_duplicate":true,"duplicate_group":null,"role_function":"Other","role_confidence":0.0},{"feature_1":-0.2916937498,"feature_2":-0.3420413152,"feature_3":-0.0778871,"feature_4":0.6283455093,"feature_5":-1.7587394864,"company_name":null,"person_name":null,"email":null,"website":null,"country":null,"issues":"missing_company_name;missing_person_name;missing_email;missing_country","has_issues":true,"suggested_email":null,"suggested_country":null,"email_confidence":0.0,"country_confidence":0.0,"corrections_applied":"","is_duplicate":true,"duplicate_group":null,"role_function":"Other","role_confidence":0.0},{"feature_1":-0.6017066122,"feature_2":-0.7567729553,"feature_3":-0.3738899693,"feature_4":-0.0122467728,"feature_5":-1.1832585127,"company_name":null,"person_name":null,"email":null,"website":null,"country":null,"issues":"missing_company_name;missing_person_name;missing_email;missing_country","has_issues":true,"suggested_email":null,"suggested_country":null,"email_confidence":0.0,"country_confidence":0.0,"corrections_applied":"","is_duplicate":true,"duplicate_group":null,"role_function":"Other","role_confidence":0.0},{"feature_1":1.8522781845,"feature_2":1.859134482,"feature_3":0.9477849512,"feature_4":-0.8972543715,"feature_5":-2.0392321778,"company_name":null,"person_name":null,"email":null,"website":null,"country":null,"issues":"missing_company_name;missing_person_name;missing_email;missing_country","has_issues":true,"suggested_email":null,"suggested_country":null,"email_confidence":0.0,"country_confidence":0.0,"corrections_applied":"","is_duplicate":true,"duplicate_group":null,"role_function":"Other","role_confidence":0.0},{"feature_1":-0.0134972247,"feature_2":-0.1197275961,"feature_3":-0.0021914284,"feature_4":0.0758045582,"feature_5":-0.2694068344,"company_name":null,"person_name":null,"email":null,"website":null,"country":null,"issues":"missing_company_name;missing_person_name;missing_email;missing_country","has_issues":true,"suggested_email":null,"suggested_country":null,"email_confidence":0.0,"country_confidence":0.0,"corrections_applied":"","is_duplicate":true,"duplicate_group":null,"role_function":"Other","role_confidence":0.0},{"feature_1":-1.057710929,"feature_2":-1.0103516859,"feature_3":-0.5940154992,"feature_4":-0.6771617115,"feature_5":0.7175422558,"company_name":null,"person_name":null,"email":null,"website":null,"country":null,"issues":"missing_company_name;missing_person_name;missing_email;missing_country","has_issues":true,"suggested_email":null,"suggested_country":null,"email_confidence":0.0,"country_confidence":0.0,"corrections_applied":"","is_duplicate":true,"duplicate_group":null,"role_function":"Other","role_confidence":0.0},{"feature_1":0.8225449121,"feature_2":0.7306024887,"feature_3":0.625666865,"feature_4":0.9751197334,"feature_5":1.5023570521,"company_name":null,"person_name":null,"email":null,"website":null,"country":null,"issues":"missing_company_name;missing_person_name;missing_email;missing_country","has_issues":true,"suggested_email":null,"suggested_country":null,"email_confidence":0.0,"country_confidence":0.0,"corrections_applied":"","is_duplicate":true,"duplicate_group":null,"role_function":"Other","role_confidence":0.0},{"feature_1":-1.22084365,"feature_2":-1.0658502095,"feature_3":-0.5470299228,"feature_4":-0.1470573815,"feature_5":0.0740947804,"company_name":null,"person_name":null,"email":null,"website":null,"country":null,"issues":"missing_company_name;missing_person_name;missing_email;missing_country","has_issues":true,"suggested_email":null,"suggested_country":null,"email_confidence":0.0,"country_confidence":0.0,"corrections_applied":"","is_duplicate":true,"duplicate_group":null,"role_function":"Other","role_confidence":0.0},{"feature_1":0.208863595,"feature_2":0.1305382658,"feature_3":-0.0980824612,"feature_4":-0.8254971968,"feature_5":1.6286155456,"company_name":null,"person_name":null,"email":null,"website":null,"country":null,"issues":"missing_company_name;missing_person_name;missing_email;missing_country","has_issues":true,"suggested_email":null,"suggested_country":null,"email_confidence":0.0,"country_confidence":0.0,"corrections_applied":"","is_duplicate":true,"duplicate_group":null,"role_function":"Other","role_confidence":0.0},{"feature_1":-1.9596701239,"feature_2":-1.9918762755,"feature_3":-0.9611896305,"feature_4":-0.3213858417,"feature_5":-1.3801014582,"company_name":null,"person_name":null,"email":null,"website":null,"country":null,"issues":"missing_company_name;missing_person_name;missing_email;missing_country","has_issues":true,"suggested_email":null,"suggested_country":null,"email_confidence":0.0,"country_confidence":0.0,"corrections_applied":"","is_duplicate":true,"duplicate_group":null,"role_function":"Other","role_confidence":0.0},{"feature_1":-1.3281860489,"feature_2":-1.2468343272,"feature_3":-0.7302716709,"feature_4":0.4129314543,"feature_5":-1.7033824394,"company_name":null,"person_name":null,"email":null,"website":null,"country":null,"issues":"missing_company_name;missing_person_name;missing_email;missing_country","has_issues":true,"suggested_email":null,"suggested_country":null,"email_confidence":0.0,"country_confidence":0.0,"corrections_applied":"","is_duplicate":true,"duplicate_group":null,"role_function":"Other","role_confidence":0.0},{"feature_1":0.1968612359,"feature_2":0.0737748042,"feature_3":0.1836739514,"feature_4":-0.5637245528,"feature_5":-0.0555476989,"company_name":null,"person_name":null,"email":null,"website":null,"country":null,"issues":"missing_company_name;missing_person_name;missing_email;missing_country","has_issues":true,"suggested_email":null,"suggested_country":null,"email_confidence":0.0,"country_confidence":0.0,"corrections_applied":"","is_duplicate":true,"duplicate_group":null,"role_function":"Other","role_confidence":0.0},{"feature_1":0.73846658,"feature_2":0.7612125735,"feature_3":0.2899812162,"feature_4":-0.8222203956,"feature_5":0.3840654489,"company_name":null,"person_name":null,"email":null,"website":null,"country":null,"issues":"missing_company_name;missing_person_name;missing_email;missing_country","has_issues":true,"suggested_email":null,"suggested_country":null,"email_confidence":0.0,"country_confidence":0.0,"corrections_applied":"","is_duplicate":true,"duplicate_group":null,"role_function":"Other","role_confidence":0.0},{"feature_1":0.1713682812,"feature_2":0.3020825566,"feature_3":0.0742104964,"feature_4":0.2436872115,"feature_5":-0.0326947481,"company_name":null,"person_name":null,"email":null,"website":null,"country":null,"issues":"missing_company_name;missing_person_name;missing_email;missing_country","has_issues":true,"suggested_email":null,"suggested_country":null,"email_confidence":0.0,"country_confidence":0.0,"corrections_applied":"","is_duplicate":true,"duplicate_group":null,"role_function":"Other","role_confidence":0.0},{"feature_1":-0.1156482824,"feature_2":-0.2763966058,"feature_3":-0.0073254133,"feature_4":0.2449665711,"feature_5":-2.0674421,"company_name":null,"person_name":null,"email":null,"website":null,"country":null,"issues":"missing_company_name;missing_person_name;missing_email;missing_country","has_issues":true,"suggested_email":null,"suggested_country":null,"email_confidence":0.0,"country_confidence":0.0,"corrections_applied":"","is_duplicate":true,"duplicate_group":null,"role_function":"Other","role_confidence":0.0},{"feature_1":-0.3011036956,"feature_2":-0.2826403097,"feature_3":-0.0639763284,"feature_4":-0.5069431754,"feature_5":-0.0891200395,"company_name":null,"person_name":null,"email":null,"website":null,"country":null,"issues":"missing_company_name;missing_person_name;missing_email;missing_country","has_issues":true,"suggested_email":null,"suggested_country":null,"email_confidence":0.0,"country_confidence":0.0,"corrections_applied":"","is_duplicate":true,"duplicate_group":null,"role_function":"Other","role_confidence":0.0},{"feature_1":-1.4785219904,"feature_2":-1.4525337109,"feature_3":-0.8592906359,"feature_4":-0.4710383056,"feature_5":-1.3044695005,"company_name":null,"person_name":null,"email":null,"website":null,"country":null,"issues":"missing_company_name;missing_person_name;missing_email;missing_country","has_issues":true,"suggested_email":null,"suggested_country":null,"email_confidence":0.0,"country_confidence":0.0,"corrections_applied":"","is_duplicate":true,"duplicate_group":null,"role_function":"Other","role_confidence":0.0},{"feature_1":-0.7198442084,"feature_2":-0.6416619212,"feature_3":-0.3933722278,"feature_4":0.2320499374,"feature_5":0.6696725488,"company_name":null,"person_name":null,"email":null,"website":null,"country":null,"issues":"missing_company_name;missing_person_name;missing_email;missing_country","has_issues":true,"suggested_email":null,"suggested_country":null,"email_confidence":0.0,"country_confidence":0.0,"corrections_applied":"","is_duplicate":true,"duplicate_group":null,"role_function":"Other","role_confidence":0.0},{"feature_1":-0.460638771,"feature_2":-0.584333842,"feature_3":-0.2778139166,"feature_4":-1.4480843415,"feature_5":0.3665982461,"company_name":null,"person_name":null,"email":null,"website":null,"country":null,"issues":"missing_company_name;missing_person_name;missing_email;missing_country","has_issues":true,"suggested_email":null,"suggested_country":null,"email_confidence":0.0,"country_confidence":0.0,"corrections_applied":"","is_duplicate":true,"duplicate_group":null,"role_function":"Other","role_confidence":0.0},{"feature_1":1.0571222262,"feature_2":0.9250765649,"feature_3":0.4632281899,"feature_4":-1.4074637744,"feature_5":-0.9398797863,"company_name":null,"person_name":null,"email":null,"website":null,"country":null,"issues":"missing_company_name;missing_person_name;missing_email;missing_country","has_issues":true,"suggested_email":null,"suggested_country":null,"email_confidence":0.0,"country_confidence":0.0,"corrections_applied":"","is_duplicate":true,"duplicate_group":null,"role_function":"Other","role_confidence":0.0},{"feature_1":0.3436182896,"feature_2":0.3958124461,"feature_3":0.3483545688,"feature_4":-0.7184442213,"feature_5":-0.5138669173,"company_name":null,"person_name":null,"email":null,"website":null,"country":null,"issues":"missing_company_name;missing_person_name;missing_email;missing_country","has_issues":true,"suggested_email":null,"suggested_country":null,"email_confidence":0.0,"country_confidence":0.0,"corrections_applied":"","is_duplicate":true,"duplicate_group":null,"role_function":"Other","role_confidence":0.0},{"feature_1":-1.7630401554,"feature_2":-1.733341688,"feature_3":-0.8410219066,"feature_4":-0.2134471517,"feature_5":-1.0592135219,"company_name":null,"person_name":null,"email":null,"website":null,"country":null,"issues":"missing_company_name;missing_person_name;missing_email;missing_country","has_issues":true,"suggested_email":null,"suggested_country":null,"email_confidence":0.0,"country_confidence":0.0,"corrections_applied":"","is_duplicate":true,"duplicate_group":null,"role_function":"Other","role_confidence":0.0},{"feature_1":0.3240839694,"feature_2":0.3491332544,"feature_3":0.0359535893,"feature_4":0.3109075656,"feature_5":-0.0626790973,"company_name":null,"person_name":null,"email":null,"website":null,"country":null,"issues":"missing_company_name;missing_person_name;missing_email;missing_country","has_issues":true,"suggested_email":null,"suggested_country":null,"email_confidence":0.0,"country_confidence":0.0,"corrections_applied":"","is_duplicate":true,"duplicate_group":null,"role_function":"Other","role_confidence":0.0},{"feature_1":-0.3850822804,"feature_2":-0.3504374595,"feature_3":-0.1007549455,"feature_4":1.4753562169,"feature_5":0.9551423205,"company_name":null,"person_name":null,"email":null,"website":null,"country":null,"issues":"missing_company_name;missing_person_name;missing_email;missing_country","has_issues":true,"suggested_email":null,"suggested_country":null,"email_confidence":0.0,"country_confidence":0.0,"corrections_applied":"","is_duplicate":true,"duplicate_group":null,"role_function":"Other","role_confidence":0.0},{"feature_1":-0.6769220003,"feature_2":-0.7449244725,"feature_3":-0.1262453805,"feature_4":0.8576596232,"feature_5":-0.9857260463,"company_name":null,"person_name":null,"email":null,"website":null,"country":null,"issues":"missing_company_name;missing_person_name;missing_email;missing_country","has_issues":true,"suggested_email":null,"suggested_country":null,"email_confidence":0.0,"country_confidence":0.0,"corrections_applied":"","is_duplicate":true,"duplicate_group":null,"role_function":"Other","role_confidence":0.0},{"feature_1":0.6116762888,"feature_2":0.6349016586,"feature_3":0.4090846705,"feature_4":-0.15993853,"feature_5":0.5040465155,"company_name":null,"person_name":null,"email":null,"website":null,"country":null,"issues":"missing_company_name;missing_person_name;missing_email;missing_country","has_issues":true,"suggested_email":null,"suggested_country":null,"email_confidence":0.0,"country_confidence":0.0,"corrections_applied":"","is_duplicate":true,"duplicate_group":null,"role_function":"Other","role_confidence":0.0},{"feature_1":1.0309995225,"feature_2":1.0603067698,"feature_3":0.3635627647,"feature_4":-0.0190162079,"feature_5":-0.5302576184,"company_name":null,"person_name":null,"email":null,"website":null,"country":null,"issues":"missing_company_name;missing_person_name;missing_email;missing_country","has_issues":true,"suggested_email":null,"suggested_country":null,"email_confidence":0.0,"country_confidence":0.0,"corrections_applied":"","is_duplicate":true,"duplicate_group":null,"role_function":"Other","role_confidence":0.0},{"feature_1":0.9312801191,"feature_2":0.8598449773,"feature_3":0.4172166523,"feature_4":-1.0025293646,"feature_5":-0.7928728323,"company_name":null,"person_name":null,"email":null,"website":null,"country":null,"issues":"missing_company_name;missing_person_name;missing_email;missing_country","has_issues":true,"suggested_email":null,"suggested_country":null,"email_confidence":0.0,"country_confidence":0.0,"corrections_applied":"","is_duplicate":true,"duplicate_group":null,"role_function":"Other","role_confidence":0.0},{"feature_1":-0.8392175232,"feature_2":-0.6526400721,"feature_3":-0.2929176467,"feature_4":-0.018513136,"feature_5":-0.10703036,"company_name":null,"person_name":null,"email":null,"website":null,"country":null,"issues":"missing_company_name;missing_person_name;missing_email;missing_country","has_issues":true,"suggested_email":null,"suggested_country":null,"email_confidence":0.0,"country_confidence":0.0,"corrections_applied":"","is_duplicate":true,"duplicate_group":null,"role_function":"Other","role_confidence":0.0},{"feature_1":-0.3092123759,"feature_2":-0.2618290838,"feature_3":-0.2253731345,"feature_4":-0.2886586389,"feature_5":-1.0352423224,"company_name":null,"person_name":null,"email":null,"website":null,"country":null,"issues":"missing_company_name;missing_person_name;missing_email;missing_country","has_issues":true,"suggested_email":null,"suggested_country":null,"email_confidence":0.0,"country_confidence":0.0,"corrections_applied":"","is_duplicate":true,"duplicate_group":null,"role_function":"Other","role_confidence":0.0},{"feature_1":0.3312634314,"feature_2":0.2121330817,"feature_3":0.2100136585,"feature_4":0.3227185603,"feature_5":-0.5536493053,"company_name":null,"person_name":null,"email":null,"website":null,"country":null,"issues":"missing_company_name;missing_person_name;missing_email;missing_country","has_issues":true,"suggested_email":null,"suggested_country":null,"email_confidence":0.0,"country_confidence":0.0,"corrections_applied":"","is_duplicate":true,"duplicate_group":null,"role_function":"Other","role_confidence":0.0},{"feature_1":0.9755451271,"feature_2":1.041200488,"feature_3":0.5652359689,"feature_4":-0.8272309436,"feature_5":-1.1978778926,"company_name":null,"person_name":null,"email":null,"website":null,"country":null,"issues":"missing_company_name;missing_person_name;missing_email;missing_country","has_issues":true,"suggested_email":null,"suggested_country":null,"email_confidence":0.0,"country_confidence":0.0,"corrections_applied":"","is_duplicate":true,"duplicate_group":null,"role_function":"Other","role_confidence":0.0},{"feature_1":-0.4791742378,"feature_2":-0.5766424049,"feature_3":-0.3322801661,"feature_4":0.5193465142,"feature_5":1.9647251329,"company_name":null,"person_name":null,"email":null,"website":null,"country":null,"issues":"missing_company_name;missing_person_name;missing_email;missing_country","has_issues":true,"suggested_email":null,"suggested_country":null,"email_confidence":0.0,"country_confidence":0.0,"corrections_applied":"","is_duplicate":true,"duplicate_group":null,"role_function":"Other","role_confidence":0.0},{"feature_1":-0.1856589767,"feature_2":-0.1069505163,"feature_3":-0.0987820239,"feature_4":1.532738913,"feature_5":0.035263552,"company_name":null,"person_name":null,"email":null,"website":null,"country":null,"issues":"missing_company_name;missing_person_name;missing_email;missing_country","has_issues":true,"suggested_email":null,"suggested_country":null,"email_confidence":0.0,"country_confidence":0.0,"corrections_applied":"","is_duplicate":true,"duplicate_group":null,"role_function":"Other","role_confidence":0.0},{"feature_1":-1.106334974,"feature_2":-0.9904754161,"feature_3":-0.877294221,"feature_4":-0.1087601485,"feature_5":-0.699725508,"company_name":null,"person_name":null,"email":null,"website":null,"country":null,"issues":"missing_company_name;missing_person_name;missing_email;missing_country","has_issues":true,"suggested_email":null,"suggested_country":null,"email_confidence":0.0,"country_confidence":0.0,"corrections_applied":"","is_duplicate":true,"duplicate_group":null,"role_function":"Other","role_confidence":0.0},{"feature_1":-1.1962066241,"feature_2":-1.2782748559,"feature_3":-0.7005420762,"feature_4":0.4017117221,"feature_5":0.2139799107,"company_name":null,"person_name":null,"email":null,"website":null,"country":null,"issues":"missing_company_name;missing_person_name;missing_email;missing_country","has_issues":true,"suggested_email":null,"suggested_country":null,"email_confidence":0.0,"country_confidence":0.0,"corrections_applied":"","is_duplicate":true,"duplicate_group":null,"role_function":"Other","role_confidence":0.0},{"feature_1":0.8125258224,"feature_2":0.9088634353,"feature_3":0.3810060961,"feature_4":0.6901439917,"feature_5":-0.1123280497,"company_name":null,"person_name":null,"email":null,"website":null,"country":null,"issues":"missing_company_name;missing_person_name;missing_email;missing_country","has_issues":true,"suggested_email":null,"suggested_country":null,"email_confidence":0.0,"country_confidence":0.0,"corrections_applied":"","is_duplicate":true,"duplicate_group":null,"role_function":"Other","role_confidence":0.0},{"feature_1":1.3562400286,"feature_2":1.3975181213,"feature_3":0.5533416961,"feature_4":-0.4012204719,"feature_5":-0.2209695995,"company_name":null,"person_name":null,"email":null,"website":null,"country":null,"issues":"missing_company_name;missing_person_name;missing_email;missing_country","has_issues":true,"suggested_email":null,"suggested_country":null,"email_confidence":0.0,"country_confidence":0.0,"corrections_applied":"","is_duplicate":true,"duplicate_group":null,"role_function":"Other","role_confidence":0.0},{"feature_1":-0.0720101216,"feature_2":0.0101958944,"feature_3":0.1272360696,"feature_4":0.2240924818,"feature_5":0.6141667,"company_name":null,"person_name":null,"email":null,"website":null,"country":null,"issues":"missing_company_name;missing_person_name;missing_email;missing_country","has_issues":true,"suggested_email":null,"suggested_country":null,"email_confidence":0.0,"country_confidence":0.0,"corrections_applied":"","is_duplicate":true,"duplicate_group":null,"role_function":"Other","role_confidence":0.0},{"feature_1":1.0035328979,"feature_2":1.1932121962,"feature_3":0.3587523111,"feature_4":0.0125924008,"feature_5":0.75750771,"company_name":null,"person_name":null,"email":null,"website":null,"country":null,"issues":"missing_company_name;missing_person_name;missing_email;missing_country","has_issues":true,"suggested_email":null,"suggested_country":null,"email_confidence":0.0,"country_confidence":0.0,"corrections_applied":"","is_duplicate":true,"duplicate_group":null,"role_function":"Other","role_confidence":0.0},{"feature_1":0.361636025,"feature_2":0.3370972134,"feature_3":0.1368135639,"feature_4":0.0976760985,"feature_5":-0.5305011476,"company_name":null,"person_name":null,"email":null,"website":null,"country":null,"issues":"missing_company_name;missing_person_name;missing_email;missing_country","has_issues":true,"suggested_email":null,"suggested_country":null,"email_confidence":0.0,"country_confidence":0.0,"corrections_applied":"","is_duplicate":true,"duplicate_group":null,"role_function":"Other","role_confidence":0.0},{"feature_1":-0.6451197546,"feature_2":-0.720493371,"feature_3":-0.3094858196,"feature_4":-0.7730097839,"feature_5":-0.5758182406,"company_name":null,"person_name":null,"email":null,"website":null,"country":null,"issues":"missing_company_name;missing_person_name;missing_email;missing_country","has_issues":true,"suggested_email":null,"suggested_country":null,"email_confidence":0.0,"country_confidence":0.0,"corrections_applied":"","is_duplicate":true,"duplicate_group":null,"role_function":"Other","role_confidence":0.0},{"feature_1":0.3613956055,"feature_2":0.2724441625,"feature_3":0.3248251317,"feature_4":0.0245101743,"feature_5":-0.2750516972,"company_name":null,"person_name":null,"email":null,"website":null,"country":null,"issues":"missing_company_name;missing_person_name;missing_email;missing_country","has_issues":true,"suggested_email":null,"suggested_country":null,"email_confidence":0.0,"country_confidence":0.0,"corrections_applied":"","is_duplicate":true,"duplicate_group":null,"role_function":"Other","role_confidence":0.0},{"feature_1":1.5380365665,"feature_2":1.456455538,"feature_3":0.6254320681,"feature_4":0.4979982912,"feature_5":-2.3019211647,"company_name":null,"person_name":null,"email":null,"website":null,"country":null,"issues":"missing_company_name;missing_person_name;missing_email;missing_country","has_issues":true,"suggested_email":null,"suggested_country":null,"email_confidence":0.0,"country_confidence":0.0,"corrections_applied":"","is_duplicate":true,"duplicate_group":null,"role_function":"Other","role_confidence":0.0},{"feature_1":-0.0358260391,"feature_2":-0.0435362101,"feature_3":0.0984033557,"feature_4":1.4511436078,"feature_5":-1.5151910622,"company_name":null,"person_name":null,"email":null,"website":null,"country":null,"issues":"missing_company_name;missing_person_name;missing_email;missing_country","has_issues":true,"suggested_email":null,"suggested_country":null,"email_confidence":0.0,"country_confidence":0.0,"corrections_applied":"","is_duplicate":true,"duplicate_group":null,"role_function":"Other","role_confidence":0.0},{"feature_1":1.5646436558,"feature_2":1.5987588533,"feature_3":0.783345134,"feature_4":0.9592708261,"feature_5":1.3668742674,"company_name":null,"person_name":null,"email":null,"website":null,"country":null,"issues":"missing_company_name;missing_person_name;missing_email;missing_country","has_issues":true,"suggested_email":null,"suggested_country":null,"email_confidence":0.0,"country_confidence":0.0,"corrections_applied":"","is_duplicate":true,"duplicate_group":null,"role_function":"Other","role_confidence":0.0},{"feature_1":-2.6197451041,"feature_2":-2.5920760242,"feature_3":-1.4080234171,"feature_4":2.1531824575,"feature_5":1.6449677135,"company_name":null,"person_name":null,"email":null,"website":null,"country":null,"issues":"missing_company_name;missing_person_name;missing_email;missing_country","has_issues":true,"suggested_email":null,"suggested_country":null,"email_confidence":0.0,"country_confidence":0.0,"corrections_applied":"","is_duplicate":true,"duplicate_group":null,"role_function":"Other","role_confidence":0.0},{"feature_1":0.8219025044,"feature_2":0.9046208293,"feature_3":0.4571615996,"feature_4":-0.7673475629,"feature_5":-0.2490360396,"company_name":null,"person_name":null,"email":null,"website":null,"country":null,"issues":"missing_company_name;missing_person_name;missing_email;missing_country","has_issues":true,"suggested_email":null,"suggested_country":null,"email_confidence":0.0,"country_confidence":0.0,"corrections_applied":"","is_duplicate":true,"duplicate_group":null,"role_function":"Other","role_confidence":0.0},{"feature_1":0.0870470682,"feature_2":0.0883472574,"feature_3":0.0634295037,"feature_4":0.8723206367,"feature_5":0.5765569631,"company_name":null,"person_name":null,"email":null,"website":null,"country":null,"issues":"missing_company_name;missing_person_name;missing_email;missing_country","has_issues":true,"suggested_email":null,"suggested_country":null,"email_confidence":0.0,"country_confidence":0.0,"corrections_applied":"","is_duplicate":true,"duplicate_group":null,"role_function":"Other","role_confidence":0.0},{"feature_1":-0.2990073505,"feature_2":-0.1536539428,"feature_3":-0.2095253629,"feature_4":0.1833420057,"feature_5":0.3112501545,"company_name":null,"person_name":null,"email":null,"website":null,"country":null,"issues":"missing_company_name;missing_person_name;missing_email;missing_country","has_issues":true,"suggested_email":null,"suggested_country":null,"email_confidence":0.0,"country_confidence":0.0,"corrections_applied":"","is_duplicate":true,"duplicate_group":null,"role_function":"Other","role_confidence":0.0},{"feature_1":0.0917607765,"feature_2":0.0652950932,"feature_3":0.0528605968,"feature_4":2.1898029332,"feature_5":3.0788808085,"company_name":null,"person_name":null,"email":null,"website":null,"country":null,"issues":"missing_company_name;missing_person_name;missing_email;missing_country","has_issues":true,"suggested_email":null,"suggested_country":null,"email_confidence":0.0,"country_confidence":0.0,"corrections_applied":"","is_duplicate":true,"duplicate_group":null,"role_function":"Other","role_confidence":0.0},{"feature_1":-1.9875689146,"feature_2":-1.7155519979,"feature_3":-1.032315817,"feature_4":-0.8082982854,"feature_5":1.1195749114,"company_name":null,"person_name":null,"email":null,"website":null,"country":null,"issues":"missing_company_name;missing_person_name;missing_email;missing_country","has_issues":true,"suggested_email":null,"suggested_country":null,"email_confidence":0.0,"country_confidence":0.0,"corrections_applied":"","is_duplicate":true,"duplicate_group":null,"role_function":"Other","role_confidence":0.0},{"feature_1":-0.2196718878,"feature_2":-0.1571051531,"feature_3":-0.0984842094,"feature_4":-0.8397218422,"feature_5":-0.1279175915,"company_name":null,"person_name":null,"email":null,"website":null,"country":null,"issues":"missing_company_name;missing_person_name;missing_email;missing_country","has_issues":true,"suggested_email":null,"suggested_country":null,"email_confidence":0.0,"country_confidence":0.0,"corrections_applied":"","is_duplicate":true,"duplicate_group":null,"role_function":"Other","role_confidence":0.0},{"feature_1":0.3571125715,"feature_2":0.2713968159,"feature_3":0.2447693532,"feature_4":-0.5993926454,"feature_5":-0.9555404406,"company_name":null,"person_name":null,"email":null,"website":null,"country":null,"issues":"missing_company_name;missing_person_name;missing_email;missing_country","has_issues":true,"suggested_email":null,"suggested_country":null,"email_confidence":0.0,"country_confidence":0.0,"corrections_applied":"","is_duplicate":true,"duplicate_group":null,"role_function":"Other","role_confidence":0.0},{"feature_1":1.4778940447,"feature_2":1.3708047949,"feature_3":0.897548704,"feature_4":-2.1238957243,"feature_5":-1.6064463203,"company_name":null,"person_name":null,"email":null,"website":null,"country":null,"issues":"missing_company_name;missing_person_name;missing_email;missing_country","has_issues":true,"suggested_email":null,"suggested_country":null,"email_confidence":0.0,"country_confidence":0.0,"corrections_applied":"","is_duplicate":true,"duplicate_group":null,"role_function":"Other","role_confidence":0.0},{"feature_1":-0.5182702183,"feature_2":-0.4700229767,"feature_3":-0.382916659,"feature_4":-0.5257550217,"feature_5":0.2034636359,"company_name":null,"person_name":null,"email":null,"website":null,"country":null,"issues":"missing_company_name;missing_person_name;missing_email;missing_country","has_issues":true,"suggested_email":null,"suggested_country":null,"email_confidence":0.0,"country_confidence":0.0,"corrections_applied":"","is_duplicate":true,"duplicate_group":null,"role_function":"Other","role_confidence":0.0},{"feature_1":-0.8084936029,"feature_2":-0.8308398814,"feature_3":-0.190943464,"feature_4":-0.7591326616,"feature_5":-0.7563507453,"company_name":null,"person_name":null,"email":null,"website":null,"country":null,"issues":"missing_company_name;missing_person_name;missing_email;missing_country","has_issues":true,"suggested_email":null,"suggested_country":null,"email_confidence":0.0,"country_confidence":0.0,"corrections_applied":"","is_duplicate":true,"duplicate_group":null,"role_function":"Other","role_confidence":0.0},{"feature_1":-0.5017570436,"feature_2":-0.4303569942,"feature_3":-0.4460873017,"feature_4":0.1503937865,"feature_5":-1.4222537096,"company_name":null,"person_name":null,"email":null,"website":null,"country":null,"issues":"missing_company_name;missing_person_name;missing_email;missing_country","has_issues":true,"suggested_email":null,"suggested_country":null,"email_confidence":0.0,"country_confidence":0.0,"corrections_applied":"","is_duplicate":true,"duplicate_group":null,"role_function":"Other","role_confidence":0.0},{"feature_1":0.9154021177,"feature_2":0.9627258802,"feature_3":0.4425225493,"feature_4":0.3417559758,"feature_5":-0.6465728842,"company_name":null,"person_name":null,"email":null,"website":null,"country":null,"issues":"missing_company_name;missing_person_name;missing_email;missing_country","has_issues":true,"suggested_email":null,"suggested_country":null,"email_confidence":0.0,"country_confidence":0.0,"corrections_applied":"","is_duplicate":true,"duplicate_group":null,"role_function":"Other","role_confidence":0.0},{"feature_1":0.3287511097,"feature_2":0.3214682184,"feature_3":0.2232072755,"feature_4":1.8761708392,"feature_5":-1.0815480036,"company_name":null,"person_name":null,"email":null,"website":null,"country":null,"issues":"missing_company_name;missing_person_name;missing_email;missing_country","has_issues":true,"suggested_email":null,"suggested_country":null,"email_confidence":0.0,"country_confidence":0.0,"corrections_applied":"","is_duplicate":true,"duplicate_group":null,"role_function":"Other","role_confidence":0.0},{"feature_1":-0.5297602038,"feature_2":-0.6144395756,"feature_3":-0.2367809151,"feature_4":0.9504238382,"feature_5":1.6871416351,"company_name":null,"person_name":null,"email":null,"website":null,"country":null,"issues":"missing_company_name;missing_person_name;missing_email;missing_country","has_issues":true,"suggested_email":null,"suggested_country":null,"email_confidence":0.0,"country_confidence":0.0,"corrections_applied":"","is_duplicate":true,"duplicate_group":null,"role_function":"Other","role_confidence":0.0},{"feature_1":0.5132674331,"feature_2":0.3617827106,"feature_3":0.1943637646,"feature_4":-0.5769036557,"feature_5":0.8816397569,"company_name":null,"person_name":null,"email":null,"website":null,"country":null,"issues":"missing_company_name;missing_person_name;missing_email;missing_country","has_issues":true,"suggested_email":null,"suggested_country":null,"email_confidence":0.0,"country_confidence":0.0,"corrections_applied":"","is_duplicate":true,"duplicate_group":null,"role_function":"Other","role_confidence":0.0},{"feature_1":0.0970775493,"feature_2":0.0524260541,"feature_3":0.0277265496,"feature_4":-0.8984146713,"feature_5":-0.0079726413,"company_name":null,"person_name":null,"email":null,"website":null,"country":null,"issues":"missing_company_name;missing_person_name;missing_email;missing_country","has_issues":true,"suggested_email":null,"suggested_country":null,"email_confidence":0.0,"country_confidence":0.0,"corrections_applied":"","is_duplicate":true,"duplicate_group":null,"role_function":"Other","role_confidence":0.0},{"feature_1":0.9686449905,"feature_2":1.05428487,"feature_3":0.4350224018,"feature_4":0.4919191715,"feature_5":1.4799441389,"company_name":null,"person_name":null,"email":null,"website":null,"country":null,"issues":"missing_company_name;missing_person_name;missing_email;missing_country","has_issues":true,"suggested_email":null,"suggested_country":null,"email_confidence":0.0,"country_confidence":0.0,"corrections_applied":"","is_duplicate":true,"duplicate_group":null,"role_function":"Other","role_confidence":0.0},{"feature_1":-0.7020530939,"feature_2":-0.6806437195,"feature_3":-0.4099630226,"feature_4":-1.320233207,"feature_5":0.0773683076,"company_name":null,"person_name":null,"email":null,"website":null,"country":null,"issues":"missing_company_name;missing_person_name;missing_email;missing_country","has_issues":true,"suggested_email":null,"suggested_country":null,"email_confidence":0.0,"country_confidence":0.0,"corrections_applied":"","is_duplicate":true,"duplicate_group":null,"role_function":"Other","role_confidence":0.0},{"feature_1":-0.3276621466,"feature_2":-0.4522360245,"feature_3":-0.0788708636,"feature_4":1.8314587659,"feature_5":-0.8612842013,"company_name":null,"person_name":null,"email":null,"website":null,"country":null,"issues":"missing_company_name;missing_person_name;missing_email;missing_country","has_issues":true,"suggested_email":null,"suggested_country":null,"email_confidence":0.0,"country_confidence":0.0,"corrections_applied":"","is_duplicate":true,"duplicate_group":null,"role_function":"Other","role_confidence":0.0},{"feature_1":-0.3921081531,"feature_2":-0.3747900605,"feature_3":-0.160352528,"feature_4":1.1794401207,"feature_5":1.5231240773,"company_name":null,"person_name":null,"email":null,"website":null,"country":null,"issues":"missing_company_name;missing_person_name;missing_email;missing_country","has_issues":true,"suggested_email":null,"suggested_country":null,"email_confidence":0.0,"country_confidence":0.0,"corrections_applied":"","is_duplicate":true,"duplicate_group":null,"role_function":"Other","role_confidence":0.0},{"feature_1":-1.4635149481,"feature_2":-1.4249832102,"feature_3":-0.8010484336,"feature_4":-0.4691756521,"feature_5":0.5389100437,"company_name":null,"person_name":null,"email":null,"website":null,"country":null,"issues":"missing_company_name;missing_person_name;missing_email;missing_country","has_issues":true,"suggested_email":null,"suggested_country":null,"email_confidence":0.0,"country_confidence":0.0,"corrections_applied":"","is_duplicate":true,"duplicate_group":null,"role_function":"Other","role_confidence":0.0},{"feature_1":0.2961202771,"feature_2":0.2077345334,"feature_3":0.2380201261,"feature_4":-1.7131345291,"feature_5":-1.0372461543,"company_name":null,"person_name":null,"email":null,"website":null,"country":null,"issues":"missing_company_name;missing_person_name;missing_email;missing_country","has_issues":true,"suggested_email":null,"suggested_country":null,"email_confidence":0.0,"country_confidence":0.0,"corrections_applied":"","is_duplicate":true,"duplicate_group":null,"role_function":"Other","role_confidence":0.0},{"feature_1":0.2610552722,"feature_2":0.2764277828,"feature_3":0.1612575882,"feature_4":1.3538723742,"feature_5":-0.1903386781,"company_name":null,"person_name":null,"email":null,"website":null,"country":null,"issues":"missing_company_name;missing_person_name;missing_email;missing_country","has_issues":true,"suggested_email":null,"suggested_country":null,"email_confidence":0.0,"country_confidence":0.0,"corrections_applied":"","is_duplicate":true,"duplicate_group":null,"role_function":"Other","role_confidence":0.0},{"feature_1":0.0051134566,"feature_2":0.0109343285,"feature_3":0.0838429402,"feature_4":-0.1145398453,"feature_5":-0.8756182534,"company_name":null,"person_name":null,"email":null,"website":null,"country":null,"issues":"missing_company_name;missing_person_name;missing_email;missing_country","has_issues":true,"suggested_email":null,"suggested_country":null,"email_confidence":0.0,"country_confidence":0.0,"corrections_applied":"","is_duplicate":true,"duplicate_group":null,"role_function":"Other","role_confidence":0.0},{"feature_1":-0.2345871334,"feature_2":-0.3488841632,"feature_3":-0.0543306825,"feature_4":1.237816312,"feature_5":-1.382799731,"company_name":null,"person_name":null,"email":null,"website":null,"country":null,"issues":"missing_company_name;missing_person_name;missing_email;missing_country","has_issues":true,"suggested_email":null,"suggested_country":null,"email_confidence":0.0,"country_confidence":0.0,"corrections_applied":"","is_duplicate":true,"duplicate_group":null,"role_function":"Other","role_confidence":0.0}]